perfetto_mcp/__init__.py
perfetto_mcp/__main__.py
perfetto_mcp/connection_manager.py
perfetto_mcp/dev.py
perfetto_mcp/server.py
perfetto_mcp/resource/__init__.py
perfetto_mcp/resource/concepts.py
perfetto_mcp/resource/trace_analysis.py
perfetto_mcp/tools/__init__.py
perfetto_mcp/tools/anr_detection.py
perfetto_mcp/tools/anr_root_cause.py
perfetto_mcp/tools/base.py
perfetto_mcp/tools/binder_transaction_profiler.py
perfetto_mcp/tools/cpu_utilization.py
perfetto_mcp/tools/find_slices.py
perfetto_mcp/tools/frame_performance_summary.py
perfetto_mcp/tools/heap_dominator_tree_analyzer.py
perfetto_mcp/tools/jank_frames.py
perfetto_mcp/tools/main_thread_hotspots.py
perfetto_mcp/tools/memory_leak_detector.py
perfetto_mcp/tools/slice_info.py
perfetto_mcp/tools/sql_query.py
perfetto_mcp/tools/thread_contention_analyzer.py
perfetto_mcp/utils/__init__.py
perfetto_mcp/utils/query_helpers.py
perfetto_mcp/docs/Perfetto-MCP-Concepts.md
perfetto_mcp-0.1.3.dist-info/METADATA
perfetto_mcp-0.1.3.dist-info/WHEEL
perfetto_mcp-0.1.3.dist-info/entry_points.txt
perfetto_mcp-0.1.3.dist-info/licenses/LICENSE
perfetto_mcp-0.1.3.dist-info/RECORD
