Metadata-Version: 2.4
Name: perfetto-mcp
Version: 0.1.3
Summary: A Model Context Protocol server for analyzing Perfetto trace files.
License-File: LICENSE
Requires-Python: >=3.10
Requires-Dist: build>=1.3.0
Requires-Dist: mcp[cli]>=1.12.1
Requires-Dist: perfetto>=0.14.0
Requires-Dist: protobuf<5
Requires-Dist: twine>=6.2.0
